ruamel.dcw-0.5.0-py2.7-nspkg.pth
ruamel/dcw/__init__.py
ruamel/dcw/__main__.py
ruamel/dcw/_templates/systemd
ruamel/dcw/_templates/upstart
ruamel.dcw-0.5.0.dist-info/DESCRIPTION.rst
ruamel.dcw-0.5.0.dist-info/LICENSE.txt
ruamel.dcw-0.5.0.dist-info/METADATA
ruamel.dcw-0.5.0.dist-info/RECORD
ruamel.dcw-0.5.0.dist-info/WHEEL
ruamel.dcw-0.5.0.dist-info/entry_points.txt
ruamel.dcw-0.5.0.dist-info/metadata.json
ruamel.dcw-0.5.0.dist-info/namespace_packages.txt
ruamel.dcw-0.5.0.dist-info/top_level.txt
