Metadata-Version: 2.0
Name: ruamel.dcw
Version: 0.5.0
Summary: docker-compose wrapper allowing for user data and env. var defaults
Home-page: https://bitbucket.org/ruamel/dcw
Author: Anthon van der Neut
Author-email: a.van.der.neut@ruamel.eu
License: MIT
Platform: UNKNOWN
Classifier: Development Status :: 4 - Beta
Classifier: Intended Audience :: Developers
Classifier: License :: OSI Approved :: MIT License
Classifier: Operating System :: OS Independent
Classifier: Programming Language :: Python
Requires-Dist: docker-compose (<1.9.0,>=1.8.0)
Requires-Dist: ruamel.showoutput
Requires-Dist: ruamel.std.pathlib
Requires-Dist: ruamel.yaml (>=0.11)
